dsautils/__init__.py
dsautils/utility.py
dsautils-0.0.2.dist-info/METADATA
dsautils-0.0.2.dist-info/WHEEL
dsautils-0.0.2.dist-info/top_level.txt
dsautils-0.0.2.dist-info/RECORD
